pdf_image_extract_annotate/__init__.py
pdf_image_extract_annotate/extractor.py
pdf_image_extract_annotate/models.py
pdf_image_extract_annotate/watermarker.py
pdf_image_extract_annotate/utils/__init__.py
pdf_image_extract_annotate/utils/blob_storage.py
pdf_image_extract_annotate/utils/image_processing.py
pdf_image_extract_annotate/utils/pdf_utils.py
pdf_image_extract_annotate-1.0.0.dist-info/licenses/LICENSE
tests/__init__.py
tests/test_blob_storage.py
tests/test_extractor.py
tests/test_image_processing.py
tests/test_pdf_utils.py
tests/test_watermarker.py
pdf_image_extract_annotate-1.0.0.dist-info/METADATA
pdf_image_extract_annotate-1.0.0.dist-info/WHEEL
pdf_image_extract_annotate-1.0.0.dist-info/entry_points.txt
pdf_image_extract_annotate-1.0.0.dist-info/top_level.txt
pdf_image_extract_annotate-1.0.0.dist-info/RECORD
