Metadata-Version: 2.4
Name: pdf-image-extract-annotate
Version: 1.0.0
Summary: Extract images from PDFs and create annotated versions with watermarks
Home-page: https://github.com/thijshakkenberg/pdf-image-extract-annotate
Author: Thijs Hakkenberg
Author-email: Thijs Hakkenberg <thijs.hakkenberg@ecolab.com>
License-Expression: MIT
Keywords: pdf,image,extraction,watermark,annotation
Classifier: Development Status :: 3 - Alpha
Classifier: Intended Audience :: Developers
Classifier: Topic :: Software Development :: Libraries :: Python Modules
Classifier: Topic :: Multimedia :: Graphics :: Graphics Conversion
Classifier: Programming Language :: Python :: 3
Classifier: Programming Language :: Python :: 3.11
Classifier: Programming Language :: Python :: 3.12
Classifier: Programming Language :: Python :: 3.13
Requires-Python: >=3.8
License-File: LICENSE
Requires-Dist: PyMuPDF>=1.23.0
Requires-Dist: pydantic>=2.0.0
Provides-Extra: azure
Requires-Dist: azure-storage-blob>=12.0.0; extra == "azure"
Provides-Extra: dev
Requires-Dist: pytest>=7.0.0; extra == "dev"
Requires-Dist: pytest-asyncio>=0.21.0; extra == "dev"
Requires-Dist: black>=23.0.0; extra == "dev"
Requires-Dist: flake8>=6.0.0; extra == "dev"
Requires-Dist: mypy>=1.0.0; extra == "dev"
Dynamic: author
Dynamic: home-page
Dynamic: license-file
Dynamic: requires-python
